tox_pipenv_install/__init__.py
tox_pipenv_install/plugin.py
tox_pipenv_install-0.1.1.dist-info/LICENSE
tox_pipenv_install-0.1.1.dist-info/METADATA
tox_pipenv_install-0.1.1.dist-info/WHEEL
tox_pipenv_install-0.1.1.dist-info/entry_points.txt
tox_pipenv_install-0.1.1.dist-info/top_level.txt
tox_pipenv_install-0.1.1.dist-info/RECORD
